llm_falcon_model/__init__.py
llm_falcon_model/config_40b.json
llm_falcon_model/config_7b.json
llm_falcon_model/configuration_RW.py
llm_falcon_model/convert_to_sepweight.py
llm_falcon_model/deciders.py
llm_falcon_model/distributed.py
llm_falcon_model/falcon_tokenizer.json
llm_falcon_model/generation.py
llm_falcon_model/initialization.py
llm_falcon_model/modeling_updated.py
llm_falcon_model/run_part.py
llm_falcon_model/scoring.py
llm_falcon_model/tokenization.py
llm_falcon_model-0.7.0.dist-info/METADATA
llm_falcon_model-0.7.0.dist-info/WHEEL
llm_falcon_model-0.7.0.dist-info/top_level.txt
llm_falcon_model-0.7.0.dist-info/RECORD
