Metadata-Version: 2.1
Name: llm-falcon-model
Version: 0.7.0
Summary: Microlib for the Falcon LLM
Author-email: Hristo Vrigazov <hvrigazov@gmail.com>
Project-URL: Homepage, https://github.com/microlib-org/llm_microlibs/llm_falcon_model
Classifier: License :: OSI Approved :: MIT License
Classifier: Programming Language :: Python
Classifier: Programming Language :: Python :: 3
Requires-Python: >=3.8
Requires-Dist: torch
Requires-Dist: tokenizers
Requires-Dist: llm-sepweight
Requires-Dist: tqdm
Provides-Extra: dev
Requires-Dist: pytest ; extra == 'dev'
